bisslog/__init__.py
bisslog/domain_context.py
bisslog/typing_compat.py
bisslog/adapt_handler/__init__.py
bisslog/adapt_handler/adapt_handler.py
bisslog/adapt_handler/external_system_handler.py
bisslog/adapt_handler/file_uploader_handler.py
bisslog/adapt_handler/notifier_handler.py
bisslog/adapt_handler/publisher_handler.py
bisslog/adapt_handler/ws_manager_handler.py
bisslog/adapters/__init__.py
bisslog/adapters/base_adapter.py
bisslog/adapters/blank_adapter.py
bisslog/adapters/division.py
bisslog/adapters/tracing/__init__.py
bisslog/adapters/tracing/logging_filter.py
bisslog/adapters/tracing/opener_tracer_logging.py
bisslog/adapters/tracing/service_tracer_logging.py
bisslog/adapters/tracing/transactional_tracer_logging.py
bisslog/database/__init__.py
bisslog/database/bisslog_db.py
bisslog/exceptions/__init__.py
bisslog/exceptions/domain_exception.py
bisslog/exceptions/external_interactions_errors.py
bisslog/ports/__init__.py
bisslog/ports/notifier.py
bisslog/ports/publisher.py
bisslog/ports/upload_file.py
bisslog/ports/ws_manager.py
bisslog/ports/tracing/__init__.py
bisslog/ports/tracing/opener_tracer.py
bisslog/ports/tracing/service_tracer.py
bisslog/ports/tracing/tracer.py
bisslog/ports/tracing/transactional_tracer.py
bisslog/transactional/__init__.py
bisslog/transactional/transaction_manager.py
bisslog/transactional/transaction_traceable.py
bisslog/use_cases/__init__.py
bisslog/use_cases/use_case_base.py
bisslog/use_cases/use_case_basic.py
bisslog/use_cases/use_case_basic_async.py
bisslog/use_cases/use_case_entry_resolver.py
bisslog/use_cases/use_case_full.py
bisslog/use_cases/use_case_decorator/__init__.py
bisslog/use_cases/use_case_decorator/decorator.py
bisslog/use_cases/use_case_decorator/prepare_function.py
bisslog/use_cases/use_case_decorator/run_with_trace_async.py
bisslog/use_cases/use_case_decorator/run_with_trace_sync.py
bisslog/use_cases/use_case_decorator/utils.py
bisslog/utils/__init__.py
bisslog/utils/is_free_function.py
bisslog/utils/singleton.py
bisslog-0.0.9.dist-info/licenses/LICENSE
bisslog-0.0.9.dist-info/METADATA
bisslog-0.0.9.dist-info/WHEEL
bisslog-0.0.9.dist-info/top_level.txt
bisslog-0.0.9.dist-info/RECORD
