Metadata-Version: 2.4
Name: bisslog
Version: 0.0.9
Summary: Business logic core (bisslog-core) - A lightweight and dependency-free implementation of Hexagonal Architecture (Ports and Adapters) in Python.
Author-email: Darwin Stiven Herrera Cartagena <darwinsherrerac@gmail.com>
Project-URL: Homepage, https://github.com/darwinhc/bisslog-core-py
Keywords: hexagonal,ports,adapters,business,logic,usecase,domain,DDD
Classifier: Programming Language :: Python :: 3
Classifier: Operating System :: OS Independent
Requires-Python: >=3.7
License-File: LICENSE
Dynamic: license-file
